ser/__init__.py
ser/ser.py
ser-0.1.0.dist-info/licenses/LICENSE
ser-0.1.0.dist-info/METADATA
ser-0.1.0.dist-info/WHEEL
ser-0.1.0.dist-info/top_level.txt
ser-0.1.0.dist-info/RECORD
