Metadata-Version: 2.4
Name: ser
Version: 0.1.0
Summary: SER (Susceptible-Excited-Refractory) Model
Author-email: Fabrizio Damicelli <fabridamicelli@gmail.com>
License-Expression: MIT
Project-URL: Changelog, https://github.com/fabridamicelli/ser/blob/main/CHANGELOG.md
Project-URL: Repository, https://github.com/fabridamicelli/ser
Keywords: python,Susceptible-Excited-Refractory,dynamical-models,complex-systems,Scientific-modelling
Classifier: Operating System :: OS Independent
Classifier: Programming Language :: Python :: 3 :: Only
Classifier: Programming Language :: Python :: 3.9
Classifier: Programming Language :: Python :: 3.10
Classifier: Programming Language :: Python :: 3.11
Classifier: Programming Language :: Python :: 3.12
Classifier: Programming Language :: Python :: 3.13
Classifier: Intended Audience :: Science/Research
Classifier: Intended Audience :: Developers
Classifier: Topic :: Scientific/Engineering
Requires-Python: >=3.9
License-File: LICENSE
Requires-Dist: numpy>=1.20.3
Requires-Dist: numba>=0.56.4
Requires-Dist: scipy>=1.7.0
Dynamic: license-file
